tfmesos/__init__.py
tfmesos/scheduler.py
tfmesos/server.py
tfmesos/utils.py
tfmesos-0.0.10.data/scripts/tfrun
tfmesos-0.0.10.dist-info/METADATA
tfmesos-0.0.10.dist-info/RECORD
tfmesos-0.0.10.dist-info/WHEEL
tfmesos-0.0.10.dist-info/top_level.txt
