Metadata-Version: 2.1
Name: tfmesos
Version: 0.0.10
Summary: Tensorflow on Mesos
Home-page: UNKNOWN
Author: Zhongbo Tian
Author-email: tianzhongbo@douban.com
License: BSD License
Download-URL: https://github.com/douban/tfmesos/archive/0.0.10.tar.gz
Platform: UNKNOWN
Classifier: Intended Audience :: Developers
Classifier: License :: OSI Approved :: BSD License
Classifier: Programming Language :: Python
Classifier: Programming Language :: Python :: Implementation :: CPython
Classifier: Operating System :: POSIX :: Linux
Classifier: Topic :: Software Development :: Libraries
Provides-Extra: gpu
Provides-Extra: cpu
Requires-Dist: six
Requires-Dist: addict
Requires-Dist: pymesos (>=0.2.10)
Provides-Extra: cpu
Requires-Dist: tensorflow (>=0.8.0); extra == 'cpu'
Provides-Extra: gpu
Requires-Dist: tensorflow-gpu (>=0.8.0); extra == 'gpu'
